esi_releases/__init__.py
esi_releases/app/__init__.py
esi_releases/app/releases.py
esi_releases/data/__init__.py
esi_releases/format/__init__.py
esi_releases/format/release_metadata.py
esi_releases/format/repository_metadata.py
esi_releases/format/version.py
esi_releases/utils/__init__.py
esi_releases/utils/changelog.py
esi_releases/utils/metadata_utils.py
esi_releases-0.1.2.dist-info/LICENSE.md
esi_releases-0.1.2.dist-info/METADATA
esi_releases-0.1.2.dist-info/WHEEL
esi_releases-0.1.2.dist-info/entry_points.txt
esi_releases-0.1.2.dist-info/top_level.txt
esi_releases-0.1.2.dist-info/RECORD
