Metadata-Version: 2.1
Name: esi-releases
Version: 0.1.2
Summary: USGS lightweight utilities for package releases
Author-email: Gabe Ferragut <gferragut@usgs.gov>, Eric Thompson <emthompsone@usgs.gov>
License: Creative Commons Legal Code
Requires-Python: >=3.8
License-File: LICENSE.md
Requires-Dist: typer
Provides-Extra: build
Requires-Dist: build ; extra == 'build'
Requires-Dist: twine ; extra == 'build'
Provides-Extra: dev
Requires-Dist: build >=0.7.0 ; extra == 'dev'
Requires-Dist: black >=21 ; extra == 'dev'
Requires-Dist: flake8 >=3.9 ; extra == 'dev'
Requires-Dist: ipython >=7.26 ; extra == 'dev'
Requires-Dist: pylint >=2.17 ; extra == 'dev'
Provides-Extra: test
Requires-Dist: pytest >=6.2 ; extra == 'test'
Requires-Dist: pytest-cov >=2.12 ; extra == 'test'
Requires-Dist: pytest-console-scripts >=1.2 ; extra == 'test'
Requires-Dist: vcrpy >=4.1 ; extra == 'test'
